lunarcalendar/__init__.py
lunarcalendar/_calc.py
lunarcalendar/_compact.py
lunarcalendar/basefestival.py
lunarcalendar/color.py
lunarcalendar/command.py
lunarcalendar/converter.py
lunarcalendar/festival.py
lunarcalendar/solarterm.py
LunarCalendar_ext-0.0.1.dist-info/LICENSE
LunarCalendar_ext-0.0.1.dist-info/METADATA
LunarCalendar_ext-0.0.1.dist-info/WHEEL
LunarCalendar_ext-0.0.1.dist-info/entry_points.txt
LunarCalendar_ext-0.0.1.dist-info/top_level.txt
LunarCalendar_ext-0.0.1.dist-info/RECORD
